sassin.py
setup.py
sassin.egg-info/PKG-INFO
sassin.egg-info/SOURCES.txt
sassin.egg-info/dependency_links.txt
sassin.egg-info/requires.txt
sassin.egg-info/top_level.txt
scripts/sassin
test/test.py