Metadata-Version: 1.0
Name: sassin
Version: 0.9.2
Summary: compiles indented-SASS-syntax to CSS stylesheets
Home-page: http://github.com/boscoh/sassin
Author: Bosco Ho
Author-email: boscoh@gmail.com
License: GPLv3
Platform: UNKNOWN
